[
  {
    "rank": 13,
    "handle": "ikigai_rps",
    "country": "India"
  },
  {
    "rank": 25,
    "handle": "athulyajv",
    "country": "India"
  },
  {
    "rank": 51,
    "handle": "Armageddon2004",
    "country": "India"
  },
  {
    "rank": 53,
    "handle": "Advanceraider",
    "country": "India"
  },
  {
    "rank": 56,
    "handle": "harshita_joshi",
    "country": "India"
  },
  {
    "rank": 69,
    "handle": "AbhaySingh28",
    "country": "India"
  },
  {
    "rank": 71,
    "handle": "Samriddha_code123",
    "country": "India"
  },
  {
    "rank": 79,
    "handle": "shubhamwip",
    "country": "India"
  },
  {
    "rank": 97,
    "handle": "ADISH18",
    "country": "India"
  },
  {
    "rank": 129,
    "handle": "manish0710",
    "country": "India"
  },
  {
    "rank": 162,
    "handle": "Kandarp08",
    "country": "India"
  },
  {
    "rank": 164,
    "handle": "shubhamtiwari2321",
    "country": "India"
  },
  {
    "rank": 167,
    "handle": "KaranD",
    "country": "India"
  },
  {
    "rank": 168,
    "handle": "aditya.pratap.pal",
    "country": "India"
  },
  {
    "rank": 187,
    "handle": "TanR_1",
    "country": "India"
  },
  {
    "rank": 191,
    "handle": "chaitanya9999",
    "country": "India"
  },
  {
    "rank": 198,
    "handle": "YASH-ai-bit",
    "country": "India"
  },
  {
    "rank": 199,
    "handle": "Dhruthi_MS",
    "country": "India"
  },
  {
    "rank": 211,
    "handle": "khandelwal_nk",
    "country": "India"
  },
  {
    "rank": 212,
    "handle": "Sajal_singh24",
    "country": "India"
  },
  {
    "rank": 241,
    "handle": "himanshujoshi192005",
    "country": "India"
  },
  {
    "rank": 252,
    "handle": "pruv007",
    "country": "India"
  },
  {
    "rank": 270,
    "handle": "tsonic",
    "country": "India"
  },
  {
    "rank": 279,
    "handle": "DhvanitVaghani",
    "country": "India"
  },
  {
    "rank": 283,
    "handle": "Divyanshu_Rajput",
    "country": "India"
  },
  {
    "rank": 288,
    "handle": "ItachiCODES",
    "country": "India"
  },
  {
    "rank": 317,
    "handle": "amaidk",
    "country": "India"
  },
  {
    "rank": 323,
    "handle": "pushkardev123",
    "country": "India"
  },
  {
    "rank": 343,
    "handle": "EigenEdge",
    "country": "India"
  },
  {
    "rank": 354,
    "handle": "Dipole23",
    "country": "India"
  },
  {
    "rank": 362,
    "handle": "sumitssr",
    "country": "India"
  },
  {
    "rank": 377,
    "handle": "Dragon.Slayer",
    "country": "India"
  },
  {
    "rank": 384,
    "handle": "Rajmani_pandey",
    "country": "India"
  },
  {
    "rank": 389,
    "handle": "srabon_bhttchrj",
    "country": "India"
  },
  {
    "rank": 397,
    "handle": "RishiVerma",
    "country": "India"
  },
  {
    "rank": 409,
    "handle": "t_srk",
    "country": "India"
  },
  {
    "rank": 441,
    "handle": "ILAJ451",
    "country": "India"
  },
  {
    "rank": 447,
    "handle": "Jarvisified",
    "country": "India"
  },
  {
    "rank": 453,
    "handle": "Rahul_23M",
    "country": "India"
  },
  {
    "rank": 459,
    "handle": "Shreyansh2174",
    "country": "India"
  },
  {
    "rank": 467,
    "handle": "ayush_lingwal",
    "country": "India"
  },
  {
    "rank": 479,
    "handle": "rj_shockwave",
    "country": "India"
  },
  {
    "rank": 499,
    "handle": "lonewolf001",
    "country": "India"
  },
  {
    "rank": 515,
    "handle": "patelunique1",
    "country": "India"
  },
  {
    "rank": 521,
    "handle": "Ojazzz",
    "country": "India"
  },
  {
    "rank": 524,
    "handle": "rupeshsinghrana62",
    "country": "India"
  },
  {
    "rank": 527,
    "handle": "shubhansh_gupta",
    "country": "India"
  },
  {
    "rank": 528,
    "handle": "rachit.gupta",
    "country": "India"
  },
  {
    "rank": 538,
    "handle": "_AnshumanSingh",
    "country": "India"
  },
  {
    "rank": 548,
    "handle": "amanraj07331",
    "country": "India"
  },
  {
    "rank": 560,
    "handle": "shubhojit-mitra-dev",
    "country": "India"
  },
  {
    "rank": 568,
    "handle": "NeuralDocCrafter",
    "country": "India"
  },
  {
    "rank": 570,
    "handle": "KMC272117_Shahid",
    "country": "India"
  },
  {
    "rank": 574,
    "handle": "Subhadeep_7897",
    "country": "India"
  },
  {
    "rank": 575,
    "handle": "Siddhesh_24",
    "country": "India"
  },
  {
    "rank": 578,
    "handle": "saiashish9",
    "country": "India"
  }
]